<?xml version="1.0">
<level>
  <object type="CANNON" x="-35.0f" y="236.0f" />
  
  <object type="ACCEL_SWITCH" x="100.0f" y="270.0f" />
  
  <object type="PLATFORM" x="95.0f" y="210.0f" width="201.0f" angle="0.0f" physics="STATIC" />
  
  <object type="PLATFORM" x="190.0f" y="300.0f" width="72.0f" angle="90.0f" physics="STATIC" />
  
  <object type="PLATFORM" x="170.0f" y="160.0f" width="201.0f" angle="0.0f" physics="STATIC" />
  
  <object type="PLATFORM" x="270.0f" y="210.0f" width="126.0f" angle="90.0f" physics="STATIC" />
  
  <object type="PLATFORM" x="355.0f" y="199.0f" width="201.0f" angle="90.0f" physics="STATIC" />
  
  <object type="PLATFORM" x="271.0f" y="112.0f" width="168.0f" angle="0.0f" physics="STATIC" />
  
  <object type="PLATFORM" x="450.0f" y="212.0f" width="72.0f" angle="0.0f" physics="STATIC" />
  
  <object type="PLATFORM" x="201.0f" y="80.0f" width="72.0f" angle="90.0f" physics="STATIC" />
  
  <object type="PLATFORM" x="340.0f" y="55.0f" width="276.0f" angle="0.0f" physics="STATIC" />
  
  <object type="GOAL" x="450.0f" y="20.0f" />
  
  <object type="PLATFORM" x="80.0f" y="112.0f" width="168.0f" angle="0.0f" physics="STATIC" />
  
  <object type="PLATFORM" x="115.0f" y="55.0f" width="168.0f" angle="0.0f" physics="STATIC" />
  
</level>